{
  "version": "1.0.0",
  "currentFullBackup": {
    "id": "backup_1749973260949_fbcvq1",
    "createdAt": "2025-06-15T07:41:00.949Z",
    "filePath": "/var/folders/6q/psxprvw97dnd9v_p7vhmvnrm0000gn/T/compression-test-1749973260947/.backups-fresh2/diff-fresh2.2025-06-15T07-41-00-949Z.txt.backup",
    "size": 30
  },
  "differentialChain": [],
  "cumulativeFileStates": {
    "/var/folders/6q/psxprvw97dnd9v_p7vhmvnrm0000gn/T/compression-test-1749973260947/diff-fresh2.txt": {
      "filePath": "/var/folders/6q/psxprvw97dnd9v_p7vhmvnrm0000gn/T/compression-test-1749973260947/diff-fresh2.txt",
      "size": 30,
      "mtime": "2025-06-15T07:41:00.949Z",
      "lastBackup": "2025-06-15T07:41:00.949Z",
      "hasChanged": false
    }
  },
  "stats": {
    "totalDifferentials": 0,
    "currentChainLength": 0,
    "cumulativeSize": 0,
    "cumulativeSizeRatio": 0,
    "totalSpaceSaved": 0,
    "lastBackupAt": "2025-06-15T07:41:00.949Z",
    "timeSinceFullBackup": 0
  },
  "lastUpdated": "2025-06-15T07:41:00.949Z"
}